LICENSE.txt
MANIFEST.in
README.md
README.txt
setup.py
Menu.egg-info/PKG-INFO
Menu.egg-info/SOURCES.txt
Menu.egg-info/dependency_links.txt
Menu.egg-info/top_level.txt
menu/__init__.py
menu/menu.py
test/tests.py