Metadata-Version: 2.1
Name: Menu
Version: 3.2.1
Summary: Easily create command-line menus
Home-page: https://github.com/drich14/Menu/
Author: Dylan Richardson
Author-email: dylanrichardson1996@gmail.com
License: LICENSE.txt
Platform: UNKNOWN
